human_eval/__init__.py
human_eval/data.py
human_eval/evaluate_functional_correctness.py
human_eval/evaluation.py
human_eval/execution.py
human_eval_windows-1.0.4.dist-info/LICENSE
human_eval_windows-1.0.4.dist-info/METADATA
human_eval_windows-1.0.4.dist-info/WHEEL
human_eval_windows-1.0.4.dist-info/entry_points.txt
human_eval_windows-1.0.4.dist-info/top_level.txt
human_eval_windows-1.0.4.dist-info/RECORD
